xpresscli/__init__.py
xpresscli/models.py
xpresscli-0.1.0.dist-info/METADATA
xpresscli-0.1.0.dist-info/WHEEL
xpresscli-0.1.0.dist-info/top_level.txt
xpresscli-0.1.0.dist-info/RECORD
