Metadata-Version: 2.1
Name: xpresscli
Version: 0.1.0
Summary: Library to simplify the process of creating powerful CLI parsers
Author: Paul K Korir
Author-email: paul.korir@gmail.com
License: Apache Software License 2.0
Project-URL: homepage, https://github.com/paulkorir/xpresscli
Project-URL: documentation, https://github.com/paulkorir/xpresscli
Project-URL: repository, https://github.com/paulkorir/xpresscli
Project-URL: changelog, https://github.com/paulkorir/xpresscli
Keywords: cli,parser,command,line,interface,argument,option,subcommand,subparser,argparse,argh,click,docopt,getopt,getopts,optparse,optik,optparse,python,python3,argparse,argparse-subcommand,argparse-subparsers,argparse-subparser,argparse-subcommand-parser,argparse-subcommands,argparse
Classifier: Development Status :: 3 - Alpha
Classifier: Intended Audience :: Developers
Classifier: License :: OSI Approved :: Apache Software License
Classifier: Programming Language :: Python :: 3
Classifier: Programming Language :: Python :: 3.6
Classifier: Programming Language :: Python :: 3.7
Classifier: Programming Language :: Python :: 3.8
Classifier: Programming Language :: Python :: 3.9
Classifier: Programming Language :: Python :: 3.10
Classifier: Programming Language :: Python :: 3.11
Classifier: Programming Language :: Python :: Implementation :: CPython
Classifier: Programming Language :: Python :: Implementation :: PyPy
Requires-Python: >=3.6
